airllm/__init__.py
airllm/airllm.py
airllm/airllm_baichuan.py
airllm/airllm_base.py
airllm/airllm_chatglm.py
airllm/airllm_internlm.py
airllm/airllm_llama_mlx.py
airllm/airllm_mistral.py
airllm/airllm_mixtral.py
airllm/airllm_qwen.py
airllm/airllm_qwen2.py
airllm/auto_model.py
airllm/profiler.py
airllm/tokenization_baichuan.py
airllm/utils.py
airllm/persist/__init__.py
airllm/persist/mlx_model_persister.py
airllm/persist/model_persister.py
airllm/persist/safetensor_model_persister.py
tests/__init__.py
tests/test_automodel.py
tests/test_compression.py
airllm-2.11.0.dist-info/LICENSE
airllm-2.11.0.dist-info/METADATA
airllm-2.11.0.dist-info/WHEEL
airllm-2.11.0.dist-info/top_level.txt
airllm-2.11.0.dist-info/RECORD
