Metadata-Version: 2.1
Name: airllm
Version: 2.11.0
Summary: AirLLM allows single 4GB GPU card to run 70B large language models without quantization, distillation or pruning. 8GB vmem to run 405B Llama3.1.
Home-page: https://github.com/lyogavin/airllm
Author: Gavin Li
Author-email: gavinli@animaai.cloud
Classifier: Programming Language :: Python :: 3
Classifier: License :: OSI Approved :: MIT License
Classifier: Operating System :: OS Independent
License-File: LICENSE
Requires-Dist: tqdm
Requires-Dist: torch
Requires-Dist: transformers
Requires-Dist: accelerate
Requires-Dist: safetensors
Requires-Dist: optimum
Requires-Dist: huggingface-hub
Requires-Dist: scipy
